digital_circuit/en-decoder/vsrc/bcd7seg.sv
`timescale 1ns / 1ps
//////////////////////////////////////////////////////////////////////////////////
// Company: 
// Engineer: 
// 
// Create Date: 2023/12/11 09:26:59
// Design Name: 
// Module Name: bcd7seg
// Project Name: 
// Target Devices: 
// Tool Versions: 
// Description: 
// 
// Dependencies: 
// 
// Revision:
// Revision 0.01 - File Created
// Additional Comments:
// 
//////////////////////////////////////////////////////////////////////////////////

/*
4'h0:   h = 7'b1000000;
4'h1:   h = 7'b1111001;
4'h2:   h = 7'b0100100;
4'h3:   h = 7'b0110000;
4'h4:   h = 7'b0011001;
4'h5:   h = 7'b0010010;
4'h6:   h = 7'b0000010;
4'h7:   h = 7'b1111000;
4'h8:   h = 7'b0000000;
4'h9:   h = 7'b0010000;
4'ha:   h = 7'b0001000;
4'hb:   h = 7'b0000011;
4'hc:   h = 7'b1000110;
4'hd:   h = 7'b0100001;
4'he:   h = 7'b0000110;
4'hf:   h = 7'b0001110;
*/

module bcd7seg(
    input logic [3:0] b,
    output logic [6:0] h
);
    always_comb begin
        case (b)
					4'h0:   h = 7'b1000000;
					4'h1:   h = 7'b1111001;
					4'h2:   h = 7'b0100100;
					4'h3:   h = 7'b0110000;
					4'h4:   h = 7'b0011001;
					4'h5:   h = 7'b0010010;
					4'h6:   h = 7'b0000010;
					4'h7:   h = 7'b1111000;
					4'h8:   h = 7'b0000000;
					4'h9:   h = 7'b0010000;
					4'ha:   h = 7'b0001000;
					4'hb:   h = 7'b0000011;
					4'hc:   h = 7'b1000110;
					4'hd:   h = 7'b0100001;
					4'he:   h = 7'b0000110;
					4'hf:   h = 7'b0001110;
        endcase
    end
endmodule

digital_circuit/en-decoder/vsrc/encode83.sv
`timescale 1ns / 1ps
//////////////////////////////////////////////////////////////////////////////////
// Company: 
// Engineer: 
// 
// Create Date: 2023/12/11 09:14:39
// Design Name: 
// Module Name: encode83
// Project Name: 
// Target Devices: 
// Tool Versions: 
// Description: 
// 
// Dependencies: 
// 
// Revision:
// Revision 0.01 - File Created
// Additional Comments:
// 
//////////////////////////////////////////////////////////////////////////////////


module encode83(
    input logic [7:0] x,
    input logic ena,
    output logic [2:0] y,
    // idx为指示位，只要x中含1则为1
    output logic idx
    );

    always_comb begin
        if (ena) begin
            idx = 1;
            casez (x) 
                8'b1???????:    y = 3'b111;
                8'b01??????:    y = 3'b110;
                8'b001?????:    y = 3'b101;
                8'b0001????:    y = 3'b100;
                8'b00001???:    y = 3'b011;
                8'b000001??:    y = 3'b010;
                8'b0000001?:    y = 3'b001;
                8'b00000001:    y = 3'b000;
                default:    y = 3'b000;
            endcase
        end else begin
            idx = 0;
            y = 3'b000;
        end
    end
endmodule

digital_circuit/en-decoder/vsrc/top.sv
`timescale 1ns / 1ps
//////////////////////////////////////////////////////////////////////////////////
// Company: 
// Engineer: 
// 
// Create Date: 2023/12/11 09:50:53
// Design Name: 
// Module Name: top
// Project Name: 
// Target Devices: 
// Tool Versions: 
// Description: 
// 
// Dependencies: 
// 
// Revision:
// Revision 0.01 - File Created
// Additional Comments:
// 
//////////////////////////////////////////////////////////////////////////////////


module top(
    input logic [7:0] x,
    input logic ena,
    output logic [2:0] y,
    output logic idx,
    output logic [6:0] h
);
    encode83 u_encode3(.x(x), .ena(ena), .y(y), .idx(idx));
		/* verilator lint_off WIDTHEXPAND */
    bcd7seg u_bcd7seg(.b(y), .h(h));
endmodule

digital_circuit/en-decoder/dump.vcd
$version Generated by VerilatedVcd $end
$timescale 1ps $end

 $scope module TOP $end
  $var wire  1 $ ena $end
  $var wire  7 ' h [6:0] $end
  $var wire  1 & idx $end
  $var wire  8 # x [7:0] $end
  $var wire  3 % y [2:0] $end
  $scope module top $end
   $var wire  1 $ ena $end
   $var wire  7 ' h [6:0] $end
   $var wire  1 & idx $end
   $var wire  8 # x [7:0] $end
   $var wire  3 % y [2:0] $end
   $scope module u_bcd7seg $end
    $var wire  4 ( b [3:0] $end
    $var wire  7 ' h [6:0] $end
   $upscope $end
   $scope module u_encode3 $end
    $var wire  1 $ ena $end
    $var wire  1 & idx $end
    $var wire  8 # x [7:0] $end
    $var wire  3 % y [2:0] $end
   $upscope $end
  $upscope $end
 $upscope $end
$enddefinitions $end


#0
b00000000 #
0$
b000 %
0&
b1000000 '
b0000 (
#1
b00000001 #
#2
b00000010 #
#3
b00000011 #
#4
b00000100 #
#5
b00000101 #
#6
b00000110 #
#7
b00000111 #
#8
b00001000 #
#9
b00001001 #
#10
b00001010 #
#11
b00001011 #
#12
b00001100 #
#13
b00001101 #
#14
b00001110 #
#15
b00001111 #
#16
b00010000 #
#17
b00010001 #
#18
b00010010 #
#19
b00010011 #
#20
b00010100 #
#21
b00010101 #
#22
b00010110 #
#23
b00010111 #
#24
b00011000 #
#25
b00011001 #
#26
b00011010 #
#27
b00011011 #
#28
b00011100 #
#29
b00011101 #
#30
b00011110 #
#31
b00011111 #
#32
b00100000 #
#33
b00100001 #
#34
b00100010 #
#35
b00100011 #
#36
b00100100 #
#37
b00100101 #
#38
b00100110 #
#39
b00100111 #
#40
b00101000 #
#41
b00101001 #
#42
b00101010 #
#43
b00101011 #
#44
b00101100 #
#45
b00101101 #
#46
b00101110 #
#47
b00101111 #
#48
b00110000 #
#49
b00110001 #
#50
b00110010 #
#51
b00110011 #
#52
b00110100 #
#53
b00110101 #
#54
b00110110 #
#55
b00110111 #
#56
b00111000 #
#57
b00111001 #
#58
b00111010 #
#59
b00111011 #
#60
b00111100 #
#61
b00111101 #
#62
b00111110 #
#63
b00111111 #
#64
b01000000 #
#65
b01000001 #
#66
b01000010 #
#67
b01000011 #
#68
b01000100 #
#69
b01000101 #
#70
b01000110 #
#71
b01000111 #
#72
b01001000 #
#73
b01001001 #
#74
b01001010 #
#75
b01001011 #
#76
b01001100 #
#77
b01001101 #
#78
b01001110 #
#79
b01001111 #
#80
b01010000 #
#81
b01010001 #
#82
b01010010 #
#83
b01010011 #
#84
b01010100 #
#85
b01010101 #
#86
b01010110 #
#87
b01010111 #
#88
b01011000 #
#89
b01011001 #
#90
b01011010 #
#91
b01011011 #
#92
b01011100 #
#93
b01011101 #
#94
b01011110 #
#95
b01011111 #
#96
b01100000 #
#97
b01100001 #
#98
b01100010 #
#99
b01100011 #
#100
b01100100 #
#101
b01100101 #
#102
b01100110 #
#103
b01100111 #
#104
b01101000 #
#105
b01101001 #
#106
b01101010 #
#107
b01101011 #
#108
b01101100 #
#109
b01101101 #
#110
b01101110 #
#111
b01101111 #
#112
b01110000 #
#113
b01110001 #
#114
b01110010 #
#115
b01110011 #
#116
b01110100 #
#117
b01110101 #
#118
b01110110 #
#119
b01110111 #
#120
b01111000 #
#121
b01111001 #
#122
b01111010 #
#123
b01111011 #
#124
b01111100 #
#125
b01111101 #
#126
b01111110 #
#127
b01111111 #
#128
b10000000 #
#129
b10000001 #
#130
b10000010 #
#131
b10000011 #
#132
b10000100 #
#133
b10000101 #
#134
b10000110 #
#135
b10000111 #
#136
b10001000 #
#137
b10001001 #
#138
b10001010 #
#139
b10001011 #
#140
b10001100 #
#141
b10001101 #
#142
b10001110 #
#143
b10001111 #
#144
b10010000 #
#145
b10010001 #
#146
b10010010 #
#147
b10010011 #
#148
b10010100 #
#149
b10010101 #
#150
b10010110 #
#151
b10010111 #
#152
b10011000 #
#153
b10011001 #
#154
b10011010 #
#155
b10011011 #
#156
b10011100 #
#157
b10011101 #
#158
b10011110 #
#159
b10011111 #
#160
b10100000 #
#161
b10100001 #
#162
b10100010 #
#163
b10100011 #
#164
b10100100 #
#165
b10100101 #
#166
b10100110 #
#167
b10100111 #
#168
b10101000 #
#169
b10101001 #
#170
b10101010 #
#171
b10101011 #
#172
b10101100 #
#173
b10101101 #
#174
b10101110 #
#175
b10101111 #
#176
b10110000 #
#177
b10110001 #
#178
b10110010 #
#179
b10110011 #
#180
b10110100 #
#181
b10110101 #
#182
b10110110 #
#183
b10110111 #
#184
b10111000 #
#185
b10111001 #
#186
b10111010 #
#187
b10111011 #
#188
b10111100 #
#189
b10111101 #
#190
b10111110 #
#191
b10111111 #
#192
b11000000 #
#193
b11000001 #
#194
b11000010 #
#195
b11000011 #
#196
b11000100 #
#197
b11000101 #
#198
b11000110 #
#199
b11000111 #
#200
b11001000 #
#201
b11001001 #
#202
b11001010 #
#203
b11001011 #
#204
b11001100 #
#205
b11001101 #
#206
b11001110 #
#207
b11001111 #
#208
b11010000 #
#209
b11010001 #
#210
b11010010 #
#211
b11010011 #
#212
b11010100 #
#213
b11010101 #
#214
b11010110 #
#215
b11010111 #
#216
b11011000 #
#217
b11011001 #
#218
b11011010 #
#219
b11011011 #
#220
b11011100 #
#221
b11011101 #
#222
b11011110 #
#223
b11011111 #
#224
b11100000 #
#225
b11100001 #
#226
b11100010 #
#227
b11100011 #
#228
b11100100 #
#229
b11100101 #
#230
b11100110 #
#231
b11100111 #
#232
b11101000 #
#233
b11101001 #
#234
b11101010 #
#235
b11101011 #
#236
b11101100 #
#237
b11101101 #
#238
b11101110 #
#239
b11101111 #
#240
b11110000 #
#241
b11110001 #
#242
b11110010 #
#243
b11110011 #
#244
b11110100 #
#245
b11110101 #
#246
b11110110 #
#247
b11110111 #
#248
b11111000 #
#249
b11111001 #
#250
b11111010 #
#251
b11111011 #
#252
b11111100 #
#253
b11111101 #
#254
b11111110 #
#255
b11111111 #
#256
b00000000 #
1$
1&
#257
b00000001 #
#258
b00000010 #
b001 %
b1111001 '
b0001 (
#259
b00000011 #
#260
b00000100 #
b010 %
b0100100 '
b0010 (
#261
b00000101 #
#262
b00000110 #
#263
b00000111 #
#264
b00001000 #
b011 %
b0110000 '
b0011 (
#265
b00001001 #
#266
b00001010 #
#267
b00001011 #
#268
b00001100 #
#269
b00001101 #
#270
b00001110 #
#271
b00001111 #
#272
b00010000 #
b100 %
b0011001 '
b0100 (
#273
b00010001 #
#274
b00010010 #
#275
b00010011 #
#276
b00010100 #
#277
b00010101 #
#278
b00010110 #
#279
b00010111 #
#280
b00011000 #
#281
b00011001 #
#282
b00011010 #
#283
b00011011 #
#284
b00011100 #
#285
b00011101 #
#286
b00011110 #
#287
b00011111 #
#288
b00100000 #
b101 %
b0010010 '
b0101 (
#289
b00100001 #
#290
b00100010 #
#291
b00100011 #
#292
b00100100 #
#293
b00100101 #
#294
b00100110 #
#295
b00100111 #
#296
b00101000 #
#297
b00101001 #
#298
b00101010 #
#299
b00101011 #
#300
b00101100 #
#301
b00101101 #
#302
b00101110 #
#303
b00101111 #
#304
b00110000 #
#305
b00110001 #
#306
b00110010 #
#307
b00110011 #
#308
b00110100 #
#309
b00110101 #
#310
b00110110 #
#311
b00110111 #
#312
b00111000 #
#313
b00111001 #
#314
b00111010 #
#315
b00111011 #
#316
b00111100 #
#317
b00111101 #
#318
b00111110 #
#319
b00111111 #
#320
b01000000 #
b110 %
b0000010 '
b0110 (
#321
b01000001 #
#322
b01000010 #
#323
b01000011 #
#324
b01000100 #
#325
b01000101 #
#326
b01000110 #
#327
b01000111 #
#328
b01001000 #
#329
b01001001 #
#330
b01001010 #
#331
b01001011 #
#332
b01001100 #
#333
b01001101 #
#334
b01001110 #
#335
b01001111 #
#336
b01010000 #
#337
b01010001 #
#338
b01010010 #
#339
b01010011 #
#340
b01010100 #
#341
b01010101 #
#342
b01010110 #
#343
b01010111 #
#344
b01011000 #
#345
b01011001 #
#346
b01011010 #
#347
b01011011 #
#348
b01011100 #
#349
b01011101 #
#350
b01011110 #
#351
b01011111 #
#352
b01100000 #
#353
b01100001 #
#354
b01100010 #
#355
b01100011 #
#356
b01100100 #
#357
b01100101 #
#358
b01100110 #
#359
b01100111 #
#360
b01101000 #
#361
b01101001 #
#362
b01101010 #
#363
b01101011 #
#364
b01101100 #
#365
b01101101 #
#366
b01101110 #
#367
b01101111 #
#368
b01110000 #
#369
b01110001 #
#370
b01110010 #
#371
b01110011 #
#372
b01110100 #
#373
b01110101 #
#374
b01110110 #
#375
b01110111 #
#376
b01111000 #
#377
b01111001 #
#378
b01111010 #
#379
b01111011 #
#380
b01111100 #
#381
b01111101 #
#382
b01111110 #
#383
b01111111 #
#384
b10000000 #
b111 %
b1111000 '
b0111 (
#385
b10000001 #
#386
b10000010 #
#387
b10000011 #
#388
b10000100 #
#389
b10000101 #
#390
b10000110 #
#391
b10000111 #
#392
b10001000 #
#393
b10001001 #
#394
b10001010 #
#395
b10001011 #
#396
b10001100 #
#397
b10001101 #
#398
b10001110 #
#399
b10001111 #
#400
b10010000 #
#401
b10010001 #
#402
b10010010 #
#403
b10010011 #
#404
b10010100 #
#405
b10010101 #
#406
b10010110 #
#407
b10010111 #
#408
b10011000 #
#409
b10011001 #
#410
b10011010 #
#411
b10011011 #
#412
b10011100 #
#413
b10011101 #
#414
b10011110 #
#415
b10011111 #
#416
b10100000 #
#417
b10100001 #
#418
b10100010 #
#419
b10100011 #
#420
b10100100 #
#421
b10100101 #
#422
b10100110 #
#423
b10100111 #
#424
b10101000 #
#425
b10101001 #
#426
b10101010 #
#427
b10101011 #
#428
b10101100 #
#429
b10101101 #
#430
b10101110 #
#431
b10101111 #
#432
b10110000 #
#433
b10110001 #
#434
b10110010 #
#435
b10110011 #
#436
b10110100 #
#437
b10110101 #
#438
b10110110 #
#439
b10110111 #
#440
b10111000 #
#441
b10111001 #
#442
b10111010 #
#443
b10111011 #
#444
b10111100 #
#445
b10111101 #
#446
b10111110 #
#447
b10111111 #
#448
b11000000 #
#449
b11000001 #
#450
b11000010 #
#451
b11000011 #
#452
b11000100 #
#453
b11000101 #
#454
b11000110 #
#455
b11000111 #
#456
b11001000 #
#457
b11001001 #
#458
b11001010 #
#459
b11001011 #
#460
b11001100 #
#461
b11001101 #
#462
b11001110 #
#463
b11001111 #
#464
b11010000 #
#465
b11010001 #
#466
b11010010 #
#467
b11010011 #
#468
b11010100 #
#469
b11010101 #
#470
b11010110 #
#471
b11010111 #
#472
b11011000 #
#473
b11011001 #
#474
b11011010 #
#475
b11011011 #
#476
b11011100 #
#477
b11011101 #
#478
b11011110 #
#479
b11011111 #
#480
b11100000 #
#481
b11100001 #
#482
b11100010 #
#483
b11100011 #
#484
b11100100 #
#485
b11100101 #
#486
b11100110 #
#487
b11100111 #
#488
b11101000 #
#489
b11101001 #
#490
b11101010 #
#491
b11101011 #
#492
b11101100 #
#493
b11101101 #
#494
b11101110 #
#495
b11101111 #
#496
b11110000 #
#497
b11110001 #
#498
b11110010 #
#499
b11110011 #
#500
b11110100 #
#501
b11110101 #
#502
b11110110 #
#503
b11110111 #
#504
b11111000 #
#505
b11111001 #
#506
b11111010 #
#507
b11111011 #
#508
b11111100 #
#509
b11111101 #
#510
b11111110 #
#511
b11111111 #
