digital_circuit/shift-reg/vsrc/top.v
module top (
    input wire clk          ,
    input wire [1:0] shamt  ,
    input wire [7:0] din    ,

    output reg [7:0] data
);
    // shamt=00 reset, 01 set din, 10 work, other stop
    
    always @(posedge clk) begin
        if (shamt == 2'b00) data <= 8'b0;
        else if (shamt == 2'b01) data <= din;
        else if (shamt == 2'b10) data <= {data[4] ^ data[3] ^ data[2] ^ data[0], data[7:1]};
        else data <= data;
    end

endmodule

digital_circuit/shift-reg/dump.vcd
$version Generated by VerilatedVcd $end
$timescale 1ps $end

 $scope module TOP $end
  $var wire  1 # clk $end
  $var wire  8 & data [7:0] $end
  $var wire  8 % din [7:0] $end
  $var wire  2 $ shamt [1:0] $end
  $scope module top $end
   $var wire  1 # clk $end
   $var wire  8 & data [7:0] $end
   $var wire  8 % din [7:0] $end
   $var wire  2 $ shamt [1:0] $end
  $upscope $end
 $upscope $end
$enddefinitions $end


#0
0#
b01 $
b00000001 %
b00000000 &
#1
1#
b00000001 &
#2
0#
b10 $
#3
1#
b10000000 &
#4
0#
#5
1#
b01000000 &
#6
0#
#7
1#
b00100000 &
#8
0#
#9
1#
b00010000 &
#10
0#
#11
1#
b10001000 &
#12
0#
#13
1#
b11000100 &
#14
0#
#15
1#
b11100010 &
#16
0#
#17
1#
b01110001 &
#18
0#
#19
1#
b00111000 &
#20
0#
#21
1#
b00011100 &
#22
0#
#23
1#
b10001110 &
#24
0#
#25
1#
b01000111 &
#26
0#
#27
1#
b00100011 &
#28
0#
#29
1#
b10010001 &
#30
0#
#31
1#
b01001000 &
#32
0#
#33
1#
b10100100 &
#34
0#
#35
1#
b11010010 &
#36
0#
#37
1#
b11101001 &
#38
0#
#39
1#
b01110100 &
#40
0#
#41
1#
b00111010 &
#42
0#
#43
1#
b00011101 &
#44
0#
#45
1#
b00001110 &
#46
0#
#47
1#
b00000111 &
#48
0#
#49
1#
b00000011 &
#50
0#
#51
1#
b10000001 &
#52
0#
#53
1#
b11000000 &
#54
0#
#55
1#
b01100000 &
#56
0#
#57
1#
b00110000 &
#58
0#
#59
1#
b10011000 &
#60
0#
#61
1#
b01001100 &
#62
0#
#63
1#
b00100110 &
#64
0#
#65
1#
b10010011 &
#66
0#
#67
1#
b01001001 &
#68
0#
#69
1#
b00100100 &
#70
0#
#71
1#
b10010010 &
#72
0#
#73
1#
b11001001 &
#74
0#
#75
1#
b01100100 &
#76
0#
#77
1#
b10110010 &
#78
0#
#79
1#
b11011001 &
#80
0#
#81
1#
b11101100 &
#82
0#
#83
1#
b01110110 &
#84
0#
#85
1#
b00111011 &
#86
0#
#87
1#
b10011101 &
#88
0#
#89
1#
b01001110 &
#90
0#
#91
1#
b00100111 &
#92
0#
#93
1#
b00010011 &
#94
0#
#95
1#
b00001001 &
#96
0#
#97
1#
b00000100 &
#98
0#
#99
1#
b10000010 &
#100
0#
#101
1#
b01000001 &
#102
0#
#103
1#
b10100000 &
#104
0#
#105
1#
b01010000 &
#106
0#
#107
1#
b10101000 &
#108
0#
#109
1#
b11010100 &
#110
0#
#111
1#
b01101010 &
#112
0#
#113
1#
b10110101 &
#114
0#
#115
1#
b11011010 &
#116
0#
#117
1#
b01101101 &
#118
0#
#119
1#
b10110110 &
#120
0#
#121
1#
b01011011 &
#122
0#
#123
1#
b10101101 &
#124
0#
#125
1#
b11010110 &
#126
0#
#127
1#
b01101011 &
#128
0#
#129
1#
b00110101 &
#130
0#
#131
1#
b10011010 &
#132
0#
#133
1#
b01001101 &
#134
0#
#135
1#
b10100110 &
#136
0#
#137
1#
b11010011 &
#138
0#
#139
1#
b01101001 &
#140
0#
#141
1#
b00110100 &
#142
0#
#143
1#
b00011010 &
#144
0#
#145
1#
b00001101 &
#146
0#
#147
1#
b10000110 &
#148
0#
#149
1#
b11000011 &
#150
0#
#151
1#
b11100001 &
#152
0#
#153
1#
b11110000 &
#154
0#
#155
1#
b11111000 &
#156
0#
#157
1#
b01111100 &
#158
0#
#159
1#
b10111110 &
#160
0#
#161
1#
b11011111 &
#162
0#
#163
1#
b01101111 &
#164
0#
#165
1#
b10110111 &
#166
0#
#167
1#
b11011011 &
#168
0#
#169
1#
b11101101 &
#170
0#
#171
1#
b11110110 &
#172
0#
#173
1#
b01111011 &
#174
0#
#175
1#
b10111101 &
#176
0#
#177
1#
b01011110 &
#178
0#
#179
1#
b10101111 &
#180
0#
#181
1#
b11010111 &
#182
0#
#183
1#
b11101011 &
#184
0#
#185
1#
b01110101 &
#186
0#
#187
1#
b10111010 &
#188
0#
#189
1#
b01011101 &
#190
0#
#191
1#
b00101110 &
#192
0#
#193
1#
b00010111 &
#194
0#
#195
1#
b10001011 &
#196
0#
#197
1#
b01000101 &
#198
0#
#199
1#
b00100010 &
#200
0#
#201
1#
b00010001 &
#202
0#
#203
1#
b00001000 &
#204
0#
#205
1#
b10000100 &
#206
0#
#207
1#
b11000010 &
#208
0#
#209
1#
b01100001 &
#210
0#
#211
1#
b10110000 &
#212
0#
#213
1#
b11011000 &
#214
0#
#215
1#
b01101100 &
#216
0#
#217
1#
b00110110 &
#218
0#
#219
1#
b00011011 &
#220
0#
#221
1#
b10001101 &
#222
0#
#223
1#
b11000110 &
#224
0#
#225
1#
b11100011 &
#226
0#
#227
1#
b11110001 &
#228
0#
#229
1#
b01111000 &
#230
0#
#231
1#
b00111100 &
#232
0#
#233
1#
b10011110 &
#234
0#
#235
1#
b11001111 &
#236
0#
#237
1#
b11100111 &
#238
0#
#239
1#
b01110011 &
#240
0#
#241
1#
b00111001 &
#242
0#
#243
1#
b10011100 &
#244
0#
#245
1#
b11001110 &
#246
0#
#247
1#
b01100111 &
#248
0#
#249
1#
b00110011 &
#250
0#
#251
1#
b00011001 &
#252
0#
#253
1#
b10001100 &
#254
0#
#255
1#
b01000110 &
#256
0#
#257
1#
b10100011 &
#258
0#
#259
1#
b11010001 &
#260
0#
#261
1#
b01101000 &
#262
0#
#263
1#
b10110100 &
#264
0#
#265
1#
b01011010 &
#266
0#
#267
1#
b00101101 &
#268
0#
#269
1#
b10010110 &
#270
0#
#271
1#
b01001011 &
#272
0#
#273
1#
b00100101 &
#274
0#
#275
1#
b00010010 &
#276
0#
#277
1#
b10001001 &
#278
0#
#279
1#
b01000100 &
#280
0#
#281
1#
b10100010 &
#282
0#
#283
1#
b01010001 &
#284
0#
#285
1#
b00101000 &
#286
0#
#287
1#
b10010100 &
#288
0#
#289
1#
b01001010 &
#290
0#
#291
1#
b10100101 &
#292
0#
#293
1#
b01010010 &
#294
0#
#295
1#
b10101001 &
#296
0#
#297
1#
b01010100 &
#298
0#
#299
1#
b00101010 &
#300
0#
#301
1#
b10010101 &
#302
0#
#303
1#
b11001010 &
#304
0#
#305
1#
b11100101 &
#306
0#
#307
1#
b01110010 &
#308
0#
#309
1#
b10111001 &
#310
0#
#311
1#
b11011100 &
#312
0#
#313
1#
b11101110 &
#314
0#
#315
1#
b01110111 &
#316
0#
#317
1#
b10111011 &
#318
0#
#319
1#
b11011101 &
#320
0#
#321
1#
b01101110 &
#322
0#
#323
1#
b00110111 &
#324
0#
#325
1#
b10011011 &
#326
0#
#327
1#
b11001101 &
#328
0#
#329
1#
b11100110 &
#330
0#
#331
1#
b11110011 &
#332
0#
#333
1#
b01111001 &
#334
0#
#335
1#
b10111100 &
#336
0#
#337
1#
b11011110 &
#338
0#
#339
1#
b11101111 &
#340
0#
#341
1#
b11110111 &
#342
0#
#343
1#
b11111011 &
#344
0#
#345
1#
b11111101 &
#346
0#
#347
1#
b01111110 &
#348
0#
#349
1#
b10111111 &
#350
0#
#351
1#
b01011111 &
#352
0#
#353
1#
b00101111 &
#354
0#
#355
1#
b10010111 &
#356
0#
#357
1#
b11001011 &
#358
0#
#359
1#
b01100101 &
#360
0#
#361
1#
b00110010 &
#362
0#
#363
1#
b10011001 &
#364
0#
#365
1#
b11001100 &
#366
0#
#367
1#
b01100110 &
#368
0#
#369
1#
b10110011 &
#370
0#
#371
1#
b01011001 &
#372
0#
#373
1#
b10101100 &
#374
0#
#375
1#
b01010110 &
#376
0#
#377
1#
b00101011 &
#378
0#
#379
1#
b00010101 &
#380
0#
#381
1#
b10001010 &
#382
0#
#383
1#
b11000101 &
#384
0#
#385
1#
b01100010 &
#386
0#
#387
1#
b00110001 &
#388
0#
#389
1#
b00011000 &
#390
0#
#391
1#
b00001100 &
#392
0#
#393
1#
b00000110 &
#394
0#
#395
1#
b10000011 &
#396
0#
#397
1#
b11000001 &
#398
0#
#399
1#
b11100000 &
#400
0#
#401
1#
b01110000 &
#402
0#
#403
1#
b10111000 &
#404
0#
#405
1#
b01011100 &
#406
0#
#407
1#
b10101110 &
#408
0#
#409
1#
b01010111 &
#410
0#
#411
1#
b10101011 &
#412
0#
#413
1#
b01010101 &
#414
0#
#415
1#
b10101010 &
#416
0#
#417
1#
b11010101 &
#418
0#
#419
1#
b11101010 &
#420
0#
#421
1#
b11110101 &
#422
0#
#423
1#
b11111010 &
#424
0#
#425
1#
b01111101 &
#426
0#
#427
1#
b00111110 &
#428
0#
#429
1#
b10011111 &
#430
0#
#431
1#
b01001111 &
#432
0#
#433
1#
b10100111 &
#434
0#
#435
1#
b01010011 &
#436
0#
#437
1#
b00101001 &
#438
0#
#439
1#
b00010100 &
#440
0#
#441
1#
b00001010 &
#442
0#
#443
1#
b10000101 &
#444
0#
#445
1#
b01000010 &
#446
0#
#447
1#
b00100001 &
#448
0#
#449
1#
b10010000 &
#450
0#
#451
1#
b11001000 &
#452
0#
#453
1#
b11100100 &
#454
0#
#455
1#
b11110010 &
#456
0#
#457
1#
b11111001 &
#458
0#
#459
1#
b11111100 &
#460
0#
#461
1#
b11111110 &
#462
0#
#463
1#
b11111111 &
#464
0#
#465
1#
b01111111 &
#466
0#
#467
1#
b00111111 &
#468
0#
#469
1#
b00011111 &
#470
0#
#471
1#
b00001111 &
#472
0#
#473
1#
b10000111 &
#474
0#
#475
1#
b01000011 &
#476
0#
#477
1#
b10100001 &
#478
0#
#479
1#
b11010000 &
#480
0#
#481
1#
b11101000 &
#482
0#
#483
1#
b11110100 &
#484
0#
#485
1#
b01111010 &
#486
0#
#487
1#
b00111101 &
#488
0#
#489
1#
b00011110 &
#490
0#
#491
1#
b10001111 &
#492
0#
#493
1#
b11000111 &
#494
0#
#495
1#
b01100011 &
#496
0#
#497
1#
b10110001 &
#498
0#
#499
1#
b01011000 &
#500
0#
#501
1#
b00101100 &
#502
0#
#503
1#
b00010110 &
#504
0#
b11 $
#505
1#
#506
0#
#507
1#
#508
0#
#509
1#
#510
0#
b10 $
#511
1#
b00001011 &
#512
0#
#513
1#
b00000101 &
#514
0#
#515
1#
b00000010 &
#516
0#
#517
1#
b00000001 &
#518
0#
#519
1#
b10000000 &
#520
0#
#521
1#
b01000000 &
#522
0#
#523
1#
b00100000 &
#524
0#
#525
1#
b00010000 &
#526
0#
#527
1#
b10001000 &
#528
0#
#529
1#
b11000100 &
#530
0#
#531
1#
b11100010 &
#532
0#
#533
1#
b01110001 &
#534
0#
#535
1#
b00111000 &
#536
0#
#537
1#
b00011100 &
#538
0#
#539
1#
b10001110 &
#540
0#
#541
1#
b01000111 &
#542
0#
#543
1#
b00100011 &
#544
0#
#545
1#
b10010001 &
#546
0#
#547
1#
b01001000 &
#548
0#
#549
1#
b10100100 &
#550
0#
#551
1#
b11010010 &
#552
0#
#553
1#
b11101001 &
#554
0#
#555
1#
b01110100 &
#556
0#
#557
1#
b00111010 &
#558
0#
#559
1#
b00011101 &
#560
0#
#561
1#
b00001110 &
#562
0#
#563
1#
b00000111 &
#564
0#
#565
1#
b00000011 &
#566
0#
#567
1#
b10000001 &
#568
0#
#569
1#
b11000000 &
#570
0#
#571
1#
b01100000 &
#572
0#
#573
1#
b00110000 &
#574
0#
#575
1#
b10011000 &
#576
0#
#577
1#
b01001100 &
#578
0#
#579
1#
b00100110 &
#580
0#
#581
1#
b10010011 &
#582
0#
#583
1#
b01001001 &
#584
0#
#585
1#
b00100100 &
#586
0#
#587
1#
b10010010 &
#588
0#
#589
1#
b11001001 &
#590
0#
#591
1#
b01100100 &
#592
0#
#593
1#
b10110010 &
#594
0#
#595
1#
b11011001 &
#596
0#
#597
1#
b11101100 &
#598
0#
#599
1#
b01110110 &
#600
0#
#601
1#
b00111011 &
#602
0#
#603
1#
b10011101 &
#604
0#
#605
1#
b01001110 &
#606
0#
#607
1#
b00100111 &
#608
0#
#609
1#
b00010011 &
#610
0#
#611
1#
b00001001 &
#612
0#
#613
1#
b00000100 &
#614
0#
#615
1#
b10000010 &
#616
0#
#617
1#
b01000001 &
#618
0#
#619
1#
b10100000 &
#620
0#
#621
1#
b01010000 &
#622
0#
#623
1#
b10101000 &
#624
0#
#625
1#
b11010100 &
#626
0#
#627
1#
b01101010 &
#628
0#
#629
1#
b10110101 &
#630
0#
#631
1#
b11011010 &
#632
0#
#633
1#
b01101101 &
#634
0#
#635
1#
b10110110 &
#636
0#
#637
1#
b01011011 &
#638
0#
#639
1#
b10101101 &
#640
0#
#641
1#
b11010110 &
#642
0#
#643
1#
b01101011 &
#644
0#
#645
1#
b00110101 &
#646
0#
#647
1#
b10011010 &
#648
0#
#649
1#
b01001101 &
#650
0#
#651
1#
b10100110 &
#652
0#
#653
1#
b11010011 &
#654
0#
#655
1#
b01101001 &
#656
0#
#657
1#
b00110100 &
#658
0#
#659
1#
b00011010 &
#660
0#
#661
1#
b00001101 &
#662
0#
#663
1#
b10000110 &
#664
0#
#665
1#
b11000011 &
#666
0#
#667
1#
b11100001 &
#668
0#
#669
1#
b11110000 &
#670
0#
#671
1#
b11111000 &
#672
0#
#673
1#
b01111100 &
#674
0#
#675
1#
b10111110 &
#676
0#
#677
1#
b11011111 &
#678
0#
#679
1#
b01101111 &
#680
0#
#681
1#
b10110111 &
#682
0#
#683
1#
b11011011 &
#684
0#
#685
1#
b11101101 &
#686
0#
#687
1#
b11110110 &
#688
0#
#689
1#
b01111011 &
#690
0#
#691
1#
b10111101 &
#692
0#
#693
1#
b01011110 &
#694
0#
#695
1#
b10101111 &
#696
0#
#697
1#
b11010111 &
#698
0#
#699
1#
b11101011 &
#700
0#
#701
1#
b01110101 &
#702
0#
#703
1#
b10111010 &
#704
0#
#705
1#
b01011101 &
#706
0#
#707
1#
b00101110 &
#708
0#
#709
1#
b00010111 &
#710
0#
#711
1#
b10001011 &
#712
0#
#713
1#
b01000101 &
#714
0#
#715
1#
b00100010 &
#716
0#
#717
1#
b00010001 &
#718
0#
#719
1#
b00001000 &
#720
0#
#721
1#
b10000100 &
#722
0#
#723
1#
b11000010 &
#724
0#
#725
1#
b01100001 &
#726
0#
#727
1#
b10110000 &
#728
0#
#729
1#
b11011000 &
#730
0#
#731
1#
b01101100 &
#732
0#
#733
1#
b00110110 &
#734
0#
#735
1#
b00011011 &
#736
0#
#737
1#
b10001101 &
#738
0#
#739
1#
b11000110 &
#740
0#
#741
1#
b11100011 &
#742
0#
#743
1#
b11110001 &
#744
0#
#745
1#
b01111000 &
#746
0#
#747
1#
b00111100 &
#748
0#
#749
1#
b10011110 &
#750
0#
#751
1#
b11001111 &
#752
0#
#753
1#
b11100111 &
#754
0#
#755
1#
b01110011 &
#756
0#
#757
1#
b00111001 &
#758
0#
#759
1#
b10011100 &
#760
0#
#761
1#
b11001110 &
#762
0#
#763
1#
b01100111 &
#764
0#
#765
1#
b00110011 &
#766
0#
#767
1#
b00011001 &
#768
0#
#769
1#
b10001100 &
#770
0#
#771
1#
b01000110 &
#772
0#
#773
1#
b10100011 &
#774
0#
#775
1#
b11010001 &
#776
0#
#777
1#
b01101000 &
#778
0#
#779
1#
b10110100 &
#780
0#
#781
1#
b01011010 &
#782
0#
#783
1#
b00101101 &
#784
0#
#785
1#
b10010110 &
#786
0#
#787
1#
b01001011 &
#788
0#
#789
1#
b00100101 &
#790
0#
#791
1#
b00010010 &
#792
0#
#793
1#
b10001001 &
#794
0#
#795
1#
b01000100 &
#796
0#
#797
1#
b10100010 &
#798
0#
#799
1#
b01010001 &
#800
0#
#801
1#
b00101000 &
#802
0#
#803
1#
b10010100 &
#804
0#
#805
1#
b01001010 &
#806
0#
#807
1#
b10100101 &
#808
0#
#809
1#
b01010010 &
#810
0#
#811
1#
b10101001 &
#812
0#
#813
1#
b01010100 &
#814
0#
#815
1#
b00101010 &
#816
0#
#817
1#
b10010101 &
#818
0#
#819
1#
b11001010 &
#820
0#
#821
1#
b11100101 &
#822
0#
#823
1#
b01110010 &
#824
0#
#825
1#
b10111001 &
#826
0#
#827
1#
b11011100 &
#828
0#
#829
1#
b11101110 &
#830
0#
#831
1#
b01110111 &
#832
0#
#833
1#
b10111011 &
#834
0#
#835
1#
b11011101 &
#836
0#
#837
1#
b01101110 &
#838
0#
#839
1#
b00110111 &
#840
0#
#841
1#
b10011011 &
#842
0#
#843
1#
b11001101 &
#844
0#
#845
1#
b11100110 &
#846
0#
#847
1#
b11110011 &
#848
0#
#849
1#
b01111001 &
#850
0#
#851
1#
b10111100 &
#852
0#
#853
1#
b11011110 &
#854
0#
#855
1#
b11101111 &
#856
0#
#857
1#
b11110111 &
#858
0#
#859
1#
b11111011 &
#860
0#
#861
1#
b11111101 &
#862
0#
#863
1#
b01111110 &
#864
0#
#865
1#
b10111111 &
#866
0#
#867
1#
b01011111 &
#868
0#
#869
1#
b00101111 &
#870
0#
#871
1#
b10010111 &
#872
0#
#873
1#
b11001011 &
#874
0#
#875
1#
b01100101 &
#876
0#
#877
1#
b00110010 &
#878
0#
#879
1#
b10011001 &
#880
0#
#881
1#
b11001100 &
#882
0#
#883
1#
b01100110 &
#884
0#
#885
1#
b10110011 &
#886
0#
#887
1#
b01011001 &
#888
0#
#889
1#
b10101100 &
#890
0#
#891
1#
b01010110 &
#892
0#
#893
1#
b00101011 &
#894
0#
#895
1#
b00010101 &
#896
0#
#897
1#
b10001010 &
#898
0#
#899
1#
b11000101 &
#900
0#
#901
1#
b01100010 &
#902
0#
#903
1#
b00110001 &
#904
0#
#905
1#
b00011000 &
#906
0#
#907
1#
b00001100 &
#908
0#
#909
1#
b00000110 &
#910
0#
#911
1#
b10000011 &
#912
0#
#913
1#
b11000001 &
#914
0#
#915
1#
b11100000 &
#916
0#
#917
1#
b01110000 &
#918
0#
#919
1#
b10111000 &
#920
0#
#921
1#
b01011100 &
#922
0#
#923
1#
b10101110 &
#924
0#
#925
1#
b01010111 &
#926
0#
#927
1#
b10101011 &
#928
0#
#929
1#
b01010101 &
#930
0#
#931
1#
b10101010 &
#932
0#
#933
1#
b11010101 &
#934
0#
#935
1#
b11101010 &
#936
0#
#937
1#
b11110101 &
#938
0#
#939
1#
b11111010 &
#940
0#
#941
1#
b01111101 &
#942
0#
#943
1#
b00111110 &
#944
0#
#945
1#
b10011111 &
#946
0#
#947
1#
b01001111 &
#948
0#
#949
1#
b10100111 &
#950
0#
#951
1#
b01010011 &
#952
0#
#953
1#
b00101001 &
#954
0#
#955
1#
b00010100 &
#956
0#
#957
1#
b00001010 &
#958
0#
#959
1#
b10000101 &
#960
0#
#961
1#
b01000010 &
#962
0#
#963
1#
b00100001 &
#964
0#
#965
1#
b10010000 &
#966
0#
#967
1#
b11001000 &
#968
0#
#969
1#
b11100100 &
#970
0#
#971
1#
b11110010 &
#972
0#
#973
1#
b11111001 &
#974
0#
#975
1#
b11111100 &
#976
0#
#977
1#
b11111110 &
#978
0#
#979
1#
b11111111 &
#980
0#
#981
1#
b01111111 &
#982
0#
#983
1#
b00111111 &
#984
0#
#985
1#
b00011111 &
#986
0#
#987
1#
b00001111 &
#988
0#
#989
1#
b10000111 &
#990
0#
#991
1#
b01000011 &
#992
0#
#993
1#
b10100001 &
#994
0#
#995
1#
b11010000 &
#996
0#
#997
1#
b11101000 &
#998
0#
#999
1#
b11110100 &
#1000
0#
#1001
1#
b01111010 &
#1002
0#
#1003
1#
b00111101 &
#1004
0#
#1005
1#
b00011110 &
#1006
0#
#1007
1#
b10001111 &
#1008
0#
#1009
1#
b11000111 &
